{
  "name": "CblTalnIdsMrLnSvcCatFkey",
  "properties": {
    "activities": [
      {
        "name": "copy_fileToTemp",
        "type": "Copy",
        "dependsOn": [],
        "policy": {
          "timeout": "0.12:00:00",
          "retry": 0,
          "retryIntervalInSeconds": 30,
          "secureOutput": false,
          "secureInput": false
        },
        "userProperties": [],
        "typeProperties": {
          "source": {
            "type": "DelimitedTextSource",
            "storeSettings": {
              "type": "AzureBlobStorageReadSettings",
              "recursive": true,
              "enablePartitionDiscovery": false
            },
            "formatSettings": {
              "type": "DelimitedTextReadSettings"
            }
          },
          "sink": {
            "type": "AzureSqlSink",
            "writeBehavior": "insert",
            "sqlWriterUseTableLock": false,
            "tableOption": "autoCreate",
            "preCopyScript": {
              "value": "DROP TABLE IF EXISTS @{pipeline().globalParameters.gbl_param_ids_staging}.TMP_CblTalnIdsMrLnSvcCatFkey",
              "type": "Expression"
            },
            "disableMetricsCollection": false,
            "upsertSettings": {}
          },
          "translator": {
            "type": "TabularTranslator",
            "typeConversion": true,
            "typeConversionSettings": {
              "allowDataTruncation": true,
              "treatBooleanAsNumber": false
            },
            "mappings": [
              {
                "source": {
                  "physicalType": "String",
                  "ordinal": 1
                },
                "sink": {
                  "name": "PRI_NAT_KEY_STRING",
                  "type": "String",
                  "physicalType": "String"
                }
              },
              {
                "source": {
                  "physicalType": "String",
                  "ordinal": 2
                },
                "sink": {
                  "name": "FIRST_RECYC_TS",
                  "type": "DateTime",
                  "physicalType": "DateTime"
                }
              },
              {
                "source": {
                  "physicalType": "String",
                  "ordinal": 3
                },
                "sink": {
                  "name": "MR_LN_SVC_CAT_SK",
                  "type": "Int64",
                  "physicalType": "Int64"
                }
              },
              {
                "source": {
                  "physicalType": "String",
                  "ordinal": 4
                },
                "sink": {
                  "name": "SRC_SYS_CD",
                  "type": "String",
                  "physicalType": "String"
                }
              },
              {
                "source": {
                  "physicalType": "String",
                  "ordinal": 5
                },
                "sink": {
                  "name": "MR_LN_ID",
                  "type": "String",
                  "physicalType": "String"
                }
              },
              {
                "source": {
                  "physicalType": "String",
                  "ordinal": 6
                },
                "sink": {
                  "name": "EFF_DT_SK",
                  "type": "String",
                  "physicalType": "String"
                }
              },
              {
                "source": {
                  "physicalType": "String",
                  "ordinal": 7
                },
                "sink": {
                  "name": "CRT_RUN_CYC_EXCTN_SK",
                  "type": "Int64",
                  "physicalType": "Int64"
                }
              },
              {
                "source": {
                  "physicalType": "String",
                  "ordinal": 8
                },
                "sink": {
                  "name": "LAST_UPDT_RUN_CYC_EXCTN_SK",
                  "type": "Int64",
                  "physicalType": "Int64"
                }
              },
              {
                "source": {
                  "physicalType": "String",
                  "ordinal": 9
                },
                "sink": {
                  "name": "SRC_SYS_CD_SK",
                  "type": "Int64",
                  "physicalType": "Int64"
                }
              },
              {
                "source": {
                  "physicalType": "String",
                  "ordinal": 10
                },
                "sink": {
                  "name": "ACTURL_HLTH_CST_GRP_SUM_ID",
                  "type": "String",
                  "physicalType": "String"
                }
              },
              {
                "source": {
                  "physicalType": "String",
                  "ordinal": 11
                },
                "sink": {
                  "name": "CST_MDL_UTILITY_ID",
                  "type": "String",
                  "physicalType": "String"
                }
              },
              {
                "source": {
                  "physicalType": "String",
                  "ordinal": 12
                },
                "sink": {
                  "name": "MR_LN_DESC",
                  "type": "String",
                  "physicalType": "String"
                }
              },
              {
                "source": {
                  "physicalType": "String",
                  "ordinal": 13
                },
                "sink": {
                  "name": "MR_LN_PFX_DESC",
                  "type": "String",
                  "physicalType": "String"
                }
              },
              {
                "source": {
                  "physicalType": "String",
                  "ordinal": 14
                },
                "sink": {
                  "name": "MR_LN_BODY_DESC",
                  "type": "String",
                  "physicalType": "String"
                }
              },
              {
                "source": {
                  "physicalType": "String",
                  "ordinal": 15
                },
                "sink": {
                  "name": "MR_LN_SFX_DESC",
                  "type": "String",
                  "physicalType": "String"
                }
              },
              {
                "source": {
                  "physicalType": "String",
                  "ordinal": 16
                },
                "sink": {
                  "name": "TERM_DT_SK",
                  "type": "String",
                  "physicalType": "String"
                }
              }
            ]
          }
        },
        "inputs": [
          {
            "referenceName": "ds_file_no_header",
            "type": "DatasetReference",
            "parameters": {
              "param_container": "@{pipeline().globalParameters.gbl_param_container_integrate}",
              "param_directory": "@concat(pipeline().globalParameters.gbl_param_environment, '/Jobs/DataWarehouse/MemberRisk/HCG/MrLnSvcCat/key')",
              "param_filename": "MR_LN_SVC_CAT.@{pipeline().parameters.SrcSysCd}.pkey.@{pipeline().parameters.RunID}.dat",
              "param_col_delimiter": ",",
              "param_row_delimiter": "@null",
              "param_quote": "^",
              "param_escape_character": "@null",
              "param_null_value": "@null"
            }
          }
        ],
        "outputs": [
          {
            "referenceName": "ds_ids",
            "type": "DatasetReference",
            "parameters": {
              "param_schema": "@{pipeline().globalParameters.gbl_param_ids_staging}",
              "param_table": "TMP_CblTalnIdsMrLnSvcCatFkey"
            }
          }
        ]
      },
      {
        "name": "sc_Transform",
        "type": "Script",
        "dependsOn": [
          {
            "activity": "copy_fileToTemp",
            "dependencyConditions": [
              "Succeeded"
            ]
          }
        ],
        "policy": {
          "timeout": "0.12:00:00",
          "retry": 0,
          "retryIntervalInSeconds": 30,
          "secureOutput": false,
          "secureInput": false
        },
        "userProperties": [],
        "typeProperties": {
          "scripts": [
            {
              "type": "Query",
              "text": {
                "value": "DROP TABLE IF EXISTS @{pipeline().globalParameters.gbl_param_ids_staging}.TMP2_CblTalnIdsMrLnSvcCatFkey; SELECT t.MR_LN_SVC_CAT_SK, t.MR_LN_ID, t.EFF_DT_SK, t.SRC_SYS_CD_SK, t.CRT_RUN_CYC_EXCTN_SK, t.LAST_UPDT_RUN_CYC_EXCTN_SK, t.TERM_DT_SK, t.ACTURL_HLTH_CST_GRP_SUM_ID AS ACTURL_HLTH_CST_GRP_CAT_ID, t.CST_MDL_UTILITY_ID AS CST_MDL_UNIT_OF_MESR_ID, t.MR_LN_DESC, t.MR_LN_PFX_DESC, t.MR_LN_BODY_DESC, t.MR_LN_SFX_DESC INTO @{pipeline().globalParameters.gbl_param_ids_staging}.TMP2_CblTalnIdsMrLnSvcCatFkey FROM @{pipeline().globalParameters.gbl_param_ids_staging}.TMP_CblTalnIdsMrLnSvcCatFkey t UNION ALL SELECT 1, 'NA', '1753-01-01', 1, 100, 100, '1753-01-01', 'NA', 'NA', 'NA', 'NA', 'NA', 'NA' UNION ALL SELECT 0, 'UNK', '1753-01-01', 0, 100, 100, '1753-01-01', 'UNK', 'UNK', 'UNK', 'UNK', 'UNK', 'UNK';",
                "type": "Expression"
              }
            }
          ]
        },
        "linkedServiceName": {
          "referenceName": "ids",
          "type": "LinkedServiceReference"
        }
      },
      {
        "name": "copy_tableToFile",
        "type": "Copy",
        "dependsOn": [
          {
            "activity": "sc_Transform",
            "dependencyConditions": [
              "Succeeded"
            ]
          }
        ],
        "policy": {
          "timeout": "0.12:00:00",
          "retry": 0,
          "retryIntervalInSeconds": 30,
          "secureOutput": false,
          "secureInput": false
        },
        "userProperties": [],
        "typeProperties": {
          "source": {
            "type": "AzureSqlSource",
            "queryTimeout": "02:00:00",
            "partitionOption": "None"
          },
          "sink": {
            "type": "DelimitedTextSink",
            "storeSettings": {
              "type": "AzureBlobStorageWriteSettings",
              "copyBehavior": "FlattenHierarchy"
            },
            "formatSettings": {
              "type": "DelimitedTextWriteSettings",
              "quoteAllText": true,
              "fileExtension": ".dat"
            },
            "translator": {
              "type": "TabularTranslator",
              "typeConversion": true,
              "typeConversionSettings": {
                "allowDataTruncation": true,
                "treatBooleanAsNumber": false
              },
              "mappings": [
                {
                  "source": {
                    "name": "MR_LN_SVC_CAT_SK",
                    "type": "Int64",
                    "physicalType": "Int64"
                  },
                  "sink": {
                    "name": "Col1",
                    "type": "String",
                    "physicalType": "String"
                  }
                },
                {
                  "source": {
                    "name": "MR_LN_ID",
                    "type": "String",
                    "physicalType": "String"
                  },
                  "sink": {
                    "name": "Col2",
                    "type": "String",
                    "physicalType": "String"
                  }
                },
                {
                  "source": {
                    "name": "EFF_DT_SK",
                    "type": "String",
                    "physicalType": "String"
                  },
                  "sink": {
                    "name": "Col3",
                    "type": "String",
                    "physicalType": "String"
                  }
                },
                {
                  "source": {
                    "name": "SRC_SYS_CD_SK",
                    "type": "Int64",
                    "physicalType": "Int64"
                  },
                  "sink": {
                    "name": "Col4",
                    "type": "String",
                    "physicalType": "String"
                  }
                },
                {
                  "source": {
                    "name": "CRT_RUN_CYC_EXCTN_SK",
                    "type": "Int64",
                    "physicalType": "Int64"
                  },
                  "sink": {
                    "name": "Col5",
                    "type": "String",
                    "physicalType": "String"
                  }
                },
                {
                  "source": {
                    "name": "LAST_UPDT_RUN_CYC_EXCTN_SK",
                    "type": "Int64",
                    "physicalType": "Int64"
                  },
                  "sink": {
                    "name": "Col6",
                    "type": "String",
                    "physicalType": "String"
                  }
                },
                {
                  "source": {
                    "name": "TERM_DT_SK",
                    "type": "String",
                    "physicalType": "String"
                  },
                  "sink": {
                    "name": "Col7",
                    "type": "String",
                    "physicalType": "String"
                  }
                },
                {
                  "source": {
                    "name": "ACTURL_HLTH_CST_GRP_CAT_ID",
                    "type": "String",
                    "physicalType": "String"
                  },
                  "sink": {
                    "name": "Col8",
                    "type": "String",
                    "physicalType": "String"
                  }
                },
                {
                  "source": {
                    "name": "CST_MDL_UNIT_OF_MESR_ID",
                    "type": "String",
                    "physicalType": "String"
                  },
                  "sink": {
                    "name": "Col9",
                    "type": "String",
                    "physicalType": "String"
                  }
                },
                {
                  "source": {
                    "name": "MR_LN_DESC",
                    "type": "String",
                    "physicalType": "String"
                  },
                  "sink": {
                    "name": "Col10",
                    "type": "String",
                    "physicalType": "String"
                  }
                },
                {
                  "source": {
                    "name": "MR_LN_PFX_DESC",
                    "type": "String",
                    "physicalType": "String"
                  },
                  "sink": {
                    "name": "Col11",
                    "type": "String",
                    "physicalType": "String"
                  }
                },
                {
                  "source": {
                    "name": "MR_LN_BODY_DESC",
                    "type": "String",
                    "physicalType": "String"
                  },
                  "sink": {
                    "name": "Col12",
                    "type": "String",
                    "physicalType": "String"
                  }
                },
                {
                  "source": {
                    "name": "MR_LN_SFX_DESC",
                    "type": "String",
                    "physicalType": "String"
                  },
                  "sink": {
                    "name": "Col13",
                    "type": "String",
                    "physicalType": "String"
                  }
                }
              ]
            }
          }
        },
        "inputs": [
          {
            "referenceName": "ds_ids",
            "type": "DatasetReference",
            "parameters": {
              "param_schema": "@{pipeline().globalParameters.gbl_param_ids_staging}",
              "param_table": "TMP2_CblTalnIdsMrLnSvcCatFkey"
            }
          }
        ],
        "outputs": [
          {
            "referenceName": "ds_file_no_header",
            "type": "DatasetReference",
            "parameters": {
              "param_container": "@{pipeline().globalParameters.gbl_param_container_integrate}",
              "param_directory": "@concat(pipeline().globalParameters.gbl_param_environment, '/Jobs/DataWarehouse/MemberRisk/HCG/MrLnSvcCat/load')",
              "param_filename": "MR_LN_SVC_CAT.@{pipeline().parameters.SrcSysCd}.@{pipeline().parameters.RunID}.dat",
              "param_col_delimiter": "@null",
              "param_row_delimiter": "@null",
              "param_quote": "^",
              "param_escape_character": "@null",
              "param_null_value": "@null"
            }
          }
        ]
      }
    ],
    "parameters": {
      "SrcSysCd": {
        "type": "String",
        "defaultValue": "FACETS"
      },
      "RunID": {
        "type": "String"
      }
    },
    "annotations": [],
    "folder": {
      "name": "Integrate/Jobs/DataWarehouse/MemberRisk/HCG/MrLnSvcCat"
    }
  },
  "Description": "COPYRIGHT 2009 BLUE CROSS/BLUE SHIELD OF KANSAS CITY \n\n\n\nMODIFICATIONS:\nDeveloper                          Date                 Project/Altiris #               Change Description                             Development Project      Code Reviewer            Date Reviewed\n----------------------------------      -------------------    -----------------------------------     ---------------------------------------------------------      ----------------------------------   ---------------------------------    -------------------------   \nRaja Gummadi                  2015-04-22      5460                                Originally Programmed                            IntegrateNewDevl        Kalyan Neelam              2015-04-24\n\nAnnotations:\nThis is a load ready file that will go into Load job"
}