{
  "name": "WellLifeClnclHlthScreenBalSeq",
  "type": "Microsoft.DataFactory/factories/pipelines",
  "properties": {
    "folder": {
      "name": "Integrate/Jobs/MedMgt/WellLifeHlthScrn/Seq"
    },
    "parameters": {
      "CurrDate": {
        "type": "String",
        "defaultValue": ""
      },
      "ExclusionList": {
        "type": "String",
        "defaultValue": ""
      },
      "ExtrRunCycle": {
        "type": "String",
        "defaultValue": ""
      },
      "Frequency": {
        "type": "String",
        "defaultValue": ""
      },
      "RunID": {
        "type": "String",
        "defaultValue": ""
      },
      "Source": {
        "type": "String",
        "defaultValue": ""
      },
      "SrcSysCd": {
        "type": "String",
        "defaultValue": ""
      },
      "Subject": {
        "type": "String",
        "defaultValue": ""
      },
      "Target": {
        "type": "String",
        "defaultValue": ""
      }
    },
    "variables": {
      "ErrorMessageCount": {
        "type": "String",
        "defaultValue": ""
      },
      "LinkCount": {
        "type": "String",
        "defaultValue": ""
      }
    },
    "activities": [
      {
        "name": "If_1A",
        "type": "IfCondition",
        "dependsOn": [],
        "userProperties": [],
        "typeProperties": {
          "expression": {
            "value": "@equals(contains(split(string(pipeline().parameters.ExclusionList), ';'), 'WellLifeIdsHlthScrnBalSeq'), false)",
            "type": "Expression"
          },
          "ifTrueActivities": [
            {
              "name": "WellLifeIdsHlthScrnBalSeq",
              "type": "ExecutePipeline",
              "dependsOn": [],
              "policy": {
                "secureInput": false
              },
              "userProperties": [],
              "typeProperties": {
                "pipeline": {
                  "referenceName": "WellLifeIdsHlthScrnBalSeq",
                  "type": "PipelineReference"
                },
                "waitOnCompletion": true,
                "parameters": {
                  "EmailSupport": {
                    "value": "@pipeline().globalParameters.gbl_param_EmailSupport",
                    "type": "Expression"
                  },
                  "CurrDate": {
                    "value": "@pipeline().parameters.CurrDate",
                    "type": "Expression"
                  },
                  "RunID": {
                    "value": "@pipeline().parameters.RunID",
                    "type": "Expression"
                  },
                  "ExtrRunCycle": {
                    "value": "@pipeline().parameters.ExtrRunCycle",
                    "type": "Expression"
                  },
                  "ExclusionList": {
                    "value": "@pipeline().parameters.ExclusionList",
                    "type": "Expression"
                  },
                  "Subject": {
                    "value": "@pipeline().parameters.Subject",
                    "type": "Expression"
                  },
                  "Source": {
                    "value": "@pipeline().parameters.SrcSysCd",
                    "type": "Expression"
                  },
                  "Target": {
                    "value": "@pipeline().parameters.Target",
                    "type": "Expression"
                  },
                  "Frequency": {
                    "value": "@pipeline().parameters.Frequency",
                    "type": "Expression"
                  },
                  "IDSOwner": {
                    "value": "@pipeline().globalParameters.gbl_param_IDSOwner",
                    "type": "Expression"
                  },
                  "ids_secret_name": {
                    "value": "@pipeline().globalParameters.gbl_param_IDSSecret",
                    "type": "Expression"
                  },
                  "UWSOwner": {
                    "value": "@pipeline().globalParameters.gbl_param_UWSOwner",
                    "type": "Expression"
                  },
                  "uws_secret_name": {
                    "value": "@pipeline().globalParameters.gbl_param_UWSSecret",
                    "type": "Expression"
                  },
                  "EDWFilePath": {
                    "value": "@pipeline().globalParameters.gbl_param_EDWFilePath",
                    "type": "Expression"
                  }
                }
              }
            }
          ],
          "ifFalseActivities": []
        }
      },
      {
        "name": "If_2A",
        "type": "IfCondition",
        "dependsOn": [
          {
            "activity": "If_1A",
            "dependencyConditions": [
              "Succeeded"
            ]
          }
        ],
        "userProperties": [],
        "typeProperties": {
          "expression": {
            "value": "@equals(contains(split(string(pipeline().parameters.ExclusionList), ';'), 'UwsMedMgtSubjAreaBalSumLoad'), false)",
            "type": "Expression"
          },
          "ifTrueActivities": [
            {
              "name": "UwsMedMgtSubjAreaBalSumLoad",
              "type": "DatabricksNotebook",
              "dependsOn": [],
              "policy": {
                "timeout": "12:00:00",
                "retry": 0,
                "retryIntervalInSeconds": 30,
                "secureOutput": false,
                "secureInput": false
              },
              "userProperties": [],
              "linkedServiceName": {
                "referenceName": "shareddatabricks",
                "type": "LinkedServiceReference"
              },
              "typeProperties": {
                "notebookPath": {
                  "value": "@concat(pipeline().globalParameters.gbl_param_notebook_path, '/MedMgt/Balancing/UwsMedMgtSubjAreaBalSumLoad')",
                  "type": "Expression"
                },
                "baseParameters": {
                  "UWSOwner": {
                    "value": "@pipeline().globalParameters.gbl_param_UWSOwner",
                    "type": "Expression"
                  },
                  "uws_secret_name": {
                    "value": "@pipeline().globalParameters.gbl_param_UWSSecret",
                    "type": "Expression"
                  },
                  "Target": {
                    "value": "@pipeline().parameters.Target",
                    "type": "Expression"
                  },
                  "Subject": "MED MGT",
                  "CurrDate": {
                    "value": "@pipeline().parameters.CurrDate",
                    "type": "Expression"
                  },
                  "ExtrRunCycle": {
                    "value": "@pipeline().parameters.ExtrRunCycle",
                    "type": "Expression"
                  }
                }
              }
            }
          ],
          "ifFalseActivities": []
        }
      },
      {
        "name": "UnixFileRecCnt",
        "type": "DatabricksNotebook",
        "dependsOn": [
          {
            "activity": "If_2A",
            "dependencyConditions": [
              "Succeeded"
            ]
          }
        ],
        "policy": {
          "timeout": "12:00:00",
          "retry": 0,
          "retryIntervalInSeconds": 30,
          "secureOutput": false,
          "secureInput": false
        },
        "userProperties": [],
        "linkedServiceName": {
          "referenceName": "shareddatabricks",
          "type": "LinkedServiceReference"
        },
        "typeProperties": {
          "notebookPath": {
            "value": "@concat(pipeline().globalParameters.gbl_param_routine_notebook_path, '/sequencer_routines/UnixFileRecCnt')",
            "type": "Expression"
          },
          "baseParameters": {
            "UnixFileRecCnt_a1": {
              "value": "@concat(pipeline().globalParameters.gbl_param_FilePath, '/balancing/notify')",
              "type": "Expression"
            },
            "UnixFileRecCnt_a2": "MedMgtBalancingNotification.dat",
            "EnvProjectPath": {
              "value": "",
              "type": "Expression"
            },
            "FilePath": {
              "value": "",
              "type": "Expression"
            },
            "FileName": {
              "value": "",
              "type": "Expression"
            }
          }
        }
      },
      {
        "name": "Set_ErrorMessageCount",
        "type": "SetVariable",
        "dependsOn": [
          {
            "activity": "UnixFileRecCnt",
            "dependencyConditions": [
              "Succeeded"
            ]
          }
        ],
        "policy": {
          "secureOutput": false,
          "secureInput": false
        },
        "userProperties": [],
        "typeProperties": {
          "variableName": "ErrorMessageCount",
          "value": {
            "value": "@string(activity('UnixFileRecCnt').output.runOutput)",
            "type": "Expression"
          }
        }
      },
      {
        "name": "If_3A",
        "type": "IfCondition",
        "dependsOn": [
          {
            "activity": "Set_ErrorMessageCount",
            "dependencyConditions": [
              "Succeeded"
            ]
          }
        ],
        "userProperties": [],
        "typeProperties": {
          "expression": {
            "value": "@not(equals(variables('ErrorMessageCount'), '0'))",
            "type": "Expression"
          },
          "ifTrueActivities": [
            {
              "name": "Email",
              "type": "ExecutePipeline",
              "dependsOn": [],
              "policy": {
                "secureInput": false
              },
              "userProperties": [],
              "typeProperties": {
                "pipeline": {
                  "referenceName": "Email_Notification",
                  "type": "PipelineReference"
                },
                "waitOnCompletion": true,
                "parameters": {
                  "recipients": {
                    "value": "@pipeline().globalParameters.gbl_param_EmailSupport",
                    "type": "Expression"
                  },
                  "subject": {
                    "value": "@concat(pipeline().parameters.SrcSysCd, ' Warehouse Balancing Medical Management Discrepancy ')",
                    "type": "Expression"
                  },
                  "body": "See Attached file for Balancing Errors",
                  "blobFilenames": {
                    "value": "@concat(pipeline().globalParameters.gbl_param_environment, '/balancing/notify/MedMgtBalancingNotification.dat')",
                    "type": "Expression"
                  },
                  "fromemail": {
                    "value": "@pipeline().globalParameters.gbl_param_fromemail",
                    "type": "Expression"
                  },
                  "containerName": {
                    "value": "@pipeline().globalParameters.gbl_param_container_integrate",
                    "type": "Expression"
                  }
                }
              }
            },
            {
              "name": "MvFile",
              "type": "DatabricksNotebook",
              "dependsOn": [
                {
                  "activity": "Email",
                  "dependencyConditions": [
                    "Succeeded"
                  ]
                }
              ],
              "policy": {
                "timeout": "12:00:00",
                "retry": 0,
                "retryIntervalInSeconds": 30,
                "secureOutput": false,
                "secureInput": false
              },
              "userProperties": [],
              "linkedServiceName": {
                "referenceName": "shareddatabricks",
                "type": "LinkedServiceReference"
              },
              "typeProperties": {
                "notebookPath": {
                  "value": "@concat(pipeline().globalParameters.gbl_param_scripts, '/Generic_ADLS_File_Operations')",
                  "type": "Expression"
                },
                "baseParameters": {
                  "src_file_with_path": {
                    "value": "/balancing/notify/MedMgtBalancingNotification.dat",
                    "type": "Expression"
                  },
                  "trgt_file_with_path": {
                    "value": "/balancing/notify/processed/MedMgtBalancingNotification.dat.",
                    "type": "Expression"
                  },
                  "command": "move",
                  "project": "integrate"
                }
              }
            }
          ],
          "ifFalseActivities": []
        }
      },
      {
        "name": "If_4A",
        "type": "IfCondition",
        "dependsOn": [
          {
            "activity": "If_3A",
            "dependencyConditions": [
              "Succeeded"
            ]
          }
        ],
        "userProperties": [],
        "typeProperties": {
          "expression": {
            "value": "@equals(contains(split(string(pipeline().parameters.ExclusionList), ';'), 'RowCtMedMgtRunCycUpd'), false)",
            "type": "Expression"
          },
          "ifTrueActivities": [
            {
              "name": "RowCtMedMgtRunCycUpd",
              "type": "DatabricksNotebook",
              "dependsOn": [],
              "policy": {
                "timeout": "12:00:00",
                "retry": 0,
                "retryIntervalInSeconds": 30,
                "secureOutput": false,
                "secureInput": false
              },
              "userProperties": [],
              "linkedServiceName": {
                "referenceName": "shareddatabricks",
                "type": "LinkedServiceReference"
              },
              "typeProperties": {
                "notebookPath": {
                  "value": "@concat(pipeline().globalParameters.gbl_param_notebook_path, '/MedMgt/Balancing/RowCtMedMgtRunCycUpd')",
                  "type": "Expression"
                },
                "baseParameters": {
                  "IDSOwner": {
                    "value": "@pipeline().globalParameters.gbl_param_IDSOwner",
                    "type": "Expression"
                  },
                  "ids_secret_name": {
                    "value": "@pipeline().globalParameters.gbl_param_IDSSecret",
                    "type": "Expression"
                  },
                  "BeginCycle": {
                    "value": "@pipeline().parameters.ExtrRunCycle",
                    "type": "Expression"
                  },
                  "SrcSys": {
                    "value": "@pipeline().parameters.SrcSysCd",
                    "type": "Expression"
                  },
                  "TrgtSys": {
                    "value": "@pipeline().parameters.Target",
                    "type": "Expression"
                  },
                  "SubjCd": {
                    "value": "@pipeline().parameters.Subject",
                    "type": "Expression"
                  }
                }
              }
            }
          ],
          "ifFalseActivities": []
        }
      }
    ]
  }
}